spycamera/__init__.py
spycamera/record.py
spycamera-1.0.0.dist-info/LICENSE
spycamera-1.0.0.dist-info/METADATA
spycamera-1.0.0.dist-info/WHEEL
spycamera-1.0.0.dist-info/top_level.txt
spycamera-1.0.0.dist-info/RECORD
