Metadata-Version: 2.1
Name: spycamera
Version: 1.0.0
Summary: A small package to record and save a webcamclip
Home-page: https://github.com/Official-BReep/spycamera
Author: BReep
Author-email: breep655@gmail.com
License: UNKNOWN
Project-URL: Bug Tracker, https://github.com/Official-BReep/spycamera/issues
Platform: UNKNOWN
Classifier: Programming Language :: Python :: 3
Classifier: License :: OSI Approved :: MIT License
Classifier: Operating System :: OS Independent
Requires-Python: >=3.6
License-File: LICENSE
